CREDITS.md
ojichat/__init__.py
ojichat/__main__.py
ojichat/__ver__.py
ojichat/generator/__init__.py
ojichat/generator/generator.py
ojichat/generator/message.py
ojichat/generator/pconfig.py
ojichat/pattern/__init__.py
ojichat/pattern/onara.py
ojichat/pattern/tags.py
ojichat_py-0.1.0.dist-info/METADATA
ojichat_py-0.1.0.dist-info/WHEEL
ojichat_py-0.1.0.dist-info/entry_points.txt
ojichat_py-0.1.0.dist-info/licenses/LICENSE
ojichat_py-0.1.0.dist-info/RECORD
