Metadata-Version: 2.1
Name: ojichat-py
Version: 0.1.0
Summary: Ojisan Nanchatte (ojichat) Generator
Keywords: Japanese ojichat text generator
Author-Email: Charahiro-tan <charahiro_pypi@98304.win>
License: MIT
Classifier: License :: OSI Approved :: MIT License
Classifier: Programming Language :: Python :: 3.8
Classifier: Programming Language :: Python :: 3.9
Classifier: Programming Language :: Python :: 3.10
Classifier: Programming Language :: Python :: 3.11
Project-URL: Repository, https://github.com/Charahiro-tan/ojichat.py
Requires-Python: >=3.8
Requires-Dist: jaconv>=0.3.4
Requires-Dist: gimei>=0.2.3
Requires-Dist: janome>=0.4.2
Requires-Dist: logzero>=1.7.0
